patchnetvlad/__init__.py
patchnetvlad/configs/netvlad_extract.ini
patchnetvlad/configs/performance.ini
patchnetvlad/configs/speed.ini
patchnetvlad/configs/storage.ini
patchnetvlad/configs/train.ini
patchnetvlad/dataset_gt_files/nordland.npz
patchnetvlad/dataset_gt_files/pitts30k_test.npz
patchnetvlad/dataset_gt_files/tokyo247.npz
patchnetvlad/dataset_imagenames/example_imageNames_index.txt
patchnetvlad/dataset_imagenames/example_imageNames_query.txt
patchnetvlad/dataset_imagenames/mapillarycph_imageNames_index.txt
patchnetvlad/dataset_imagenames/mapillarycph_imageNames_query.txt
patchnetvlad/dataset_imagenames/mapillarysf_imageNames_index.txt
patchnetvlad/dataset_imagenames/mapillarysf_imageNames_query.txt
patchnetvlad/dataset_imagenames/nordland_imageNames_index.txt
patchnetvlad/dataset_imagenames/nordland_imageNames_query.txt
patchnetvlad/dataset_imagenames/pitts30k_imageNames_index.txt
patchnetvlad/dataset_imagenames/pitts30k_imageNames_query.txt
patchnetvlad/dataset_imagenames/tokyo247_imageNames_index.txt
patchnetvlad/dataset_imagenames/tokyo247_imageNames_query.txt
patchnetvlad/example_images/tokyo_db.png
patchnetvlad/example_images/tokyo_query.jpg
patchnetvlad/models/__init__.py
patchnetvlad/models/local_matcher.py
patchnetvlad/models/models_generic.py
patchnetvlad/models/netvlad.py
patchnetvlad/models/patchnetvlad.py
patchnetvlad/output_features/.hidden
patchnetvlad/pretrained_models/.hidden
patchnetvlad/results/.hidden
patchnetvlad/tools/__init__.py
patchnetvlad/tools/datasets.py
patchnetvlad/tools/gen_image_file_list.py
patchnetvlad/tools/patch_matcher.py
patchnetvlad/training_tools/__init__.py
patchnetvlad/training_tools/convert_kapture_to_msls.py
patchnetvlad/training_tools/get_clusters.py
patchnetvlad/training_tools/msls.py
patchnetvlad/training_tools/tools.py
patchnetvlad/training_tools/train_epoch.py
patchnetvlad/training_tools/val.py
patchnetvlad-0.1.8.data/scripts/download_models.py
patchnetvlad-0.1.8.data/scripts/feature_extract.py
patchnetvlad-0.1.8.dist-info/LICENSE
patchnetvlad-0.1.8.dist-info/METADATA
patchnetvlad-0.1.8.dist-info/WHEEL
patchnetvlad-0.1.8.dist-info/entry_points.txt
patchnetvlad-0.1.8.dist-info/top_level.txt
patchnetvlad-0.1.8.dist-info/RECORD
