Metadata-Version: 2.1
Name: patchnetvlad
Version: 0.1.8
Summary: Patch-NetVLAD: An open-source Python implementation of the CVPR2021 paper
Home-page: https://github.com/QVPR/Patch-NetVLAD
Author: Stephen Hausler, Sourav Garg, Ming Xu, Michael Milford and Tobias Fischer
Author-email: stephen.hausler@hdr.qut.edu.au
License: MIT
Keywords: python,place recognition,image retrieval,computer vision,robotics
Classifier: Development Status :: 4 - Beta
Classifier: Intended Audience :: Developers
Classifier: License :: OSI Approved :: MIT License
Classifier: Programming Language :: Python :: 3.6
Classifier: Programming Language :: Python :: 3.7
Classifier: Programming Language :: Python :: 3.8
Classifier: Programming Language :: Python :: 3.9
Requires-Python: >=3.6
License-File: LICENSE
Requires-Dist: numpy
Requires-Dist: torch
Requires-Dist: torchvision
Requires-Dist: tqdm
Requires-Dist: scipy
Requires-Dist: Pillow
Requires-Dist: scikit-learn
Requires-Dist: faiss
Requires-Dist: natsort
Requires-Dist: matplotlib
Requires-Dist: opencv-python
